{
  "parent": "gamedataTweakDBRecord",
  "name": "gamedataAISquadType_Record",
  "flags": 66,
  "funcs": [
    {
      "fullName": "EnumComment",
      "shortName": "EnumComment",
      "return": {
        "type": "String",
        "flags": 64
      },
      "index": 5923,
      "flags": 1
    },
    {
      "fullName": "EnumName",
      "shortName": "EnumName",
      "return": {
        "type": "CName",
        "flags": 64
      },
      "index": 5924,
      "flags": 1
    },
    {
      "fullName": "Type",
      "shortName": "Type",
      "return": {
        "type": "gamedataAISquadType",
        "flags": 64
      },
      "index": 5925,
      "flags": 1
    }
  ]
}
