{
  "parent": "gamedataTweakDBRecord",
  "name": "gamedataBountyDrawTable_Record",
  "flags": 66,
  "funcs": [
    {
      "fullName": "BountyChoices",
      "shortName": "BountyChoices",
      "index": 8662,
      "flags": 1,
      "params": [
        {
          "type": "array:whandle:gamedataBounty_Record",
          "name": "outList",
          "flags": 640
        }
      ]
    },
    {
      "fullName": "BountyChoicesContains",
      "shortName": "BountyChoicesContains",
      "return": {
        "type": "Bool",
        "flags": 64
      },
      "index": 8666,
      "flags": 1,
      "params": [
        {
          "type": "whandle:gamedataBounty_Record",
          "name": "item",
          "flags": 128
        }
      ]
    },
    {
      "fullName": "GetBountyChoicesCount",
      "shortName": "GetBountyChoicesCount",
      "return": {
        "type": "Int32",
        "flags": 64
      },
      "index": 8663,
      "flags": 1
    },
    {
      "fullName": "GetBountyChoicesItem",
      "shortName": "GetBountyChoicesItem",
      "return": {
        "type": "whandle:gamedataBounty_Record",
        "flags": 64
      },
      "index": 8664,
      "flags": 1,
      "params": [
        {
          "type": "Int32",
          "name": "index",
          "flags": 128
        }
      ]
    },
    {
      "fullName": "GetBountyChoicesItemHandle",
      "shortName": "GetBountyChoicesItemHandle",
      "return": {
        "type": "handle:gamedataBounty_Record",
        "flags": 64
      },
      "index": 8665,
      "flags": 1,
      "params": [
        {
          "type": "Int32",
          "name": "index",
          "flags": 128
        }
      ]
    }
  ]
}
