{"a":"gameScriptableSystem","b":"DropPointSystem","d":0,"e":[{"a":{"a":31,"c":{"a":26,"c":{"b":"DropPointPackage"}}},"b":"packages","c":133},{"a":{"a":31,"c":{"a":26,"c":{"b":"DropPointMappinRegistrationData"}}},"b":"mappins","c":133},{"a":{"a":1},"b":"isEnabled","c":133},{"a":{"a":31,"c":{"b":"DropPointSystemLock"}},"b":"dropPointSystemLocks","c":133}],"f":[{"a":"AddDropPointSystemLock;CName","b":"AddDropPointSystemLock","d":49,"e":[{"a":{"a":14},"b":"reason","c":0}]},{"a":"CanDeposit;TweakDBIDPersistentID","b":"CanDeposit","c":{"a":1},"d":176,"e":[{"a":{"a":15},"b":"record","c":0},{"a":{"b":"gamePersistentID"},"b":"dropPoint","c":0}]},{"a":"CreatePackage;DropPointRequest","b":"CreatePackage","d":49,"e":[{"a":{"a":26,"c":{"b":"DropPointRequest"}},"b":"request","c":0}]},{"a":"GetMappinData;EntityID","b":"GetMappinData","c":{"a":26,"c":{"b":"DropPointMappinRegistrationData"}},"d":49,"e":[{"a":{"b":"entEntityID"},"b":"ownerID","c":0}]},{"a":"GetMappinSystem;","b":"GetMappinSystem","c":{"a":26,"c":{"b":"gamemappinsMappinSystem"}},"d":49},{"a":"HasItemsThatCanBeDeposited;GameObjectPersistentID","b":"HasItemsThatCanBeDeposited","c":{"a":1},"d":176,"e":[{"a":{"a":26,"c":{"b":"gameObject"}},"b":"user","c":0},{"a":{"b":"gamePersistentID"},"b":"dropPoint","c":0}]},{"a":"HasMappin;EntityID","b":"HasMappin","c":{"a":1},"d":49,"e":[{"a":{"b":"entEntityID"},"b":"ownerID","c":0}]},{"a":"HasMeaningfulItems;script_ref<array<gameItemData>>PersistentID","b":"HasMeaningfulItems","c":{"a":1},"d":178,"e":[{"a":{"a":28,"c":{"a":31,"c":{"a":27,"c":{"b":"gameItemData"}}}},"b":"items","c":0},{"a":{"b":"gamePersistentID"},"b":"dropPoint","c":0}]},{"a":"HideDropPointMappins;Bool","b":"HideDropPointMappins","d":49,"e":[{"a":{"a":1},"b":"informDevice","c":4}]},{"a":"Is;TweakDBIDDropPointPackageStatus","b":"Is","c":{"a":1},"d":176,"e":[{"a":{"a":15},"b":"record","c":0},{"a":{"b":"DropPointPackageStatus"},"b":"status","c":0}]},{"a":"IsActive;TweakDBID","b":"IsActive","c":{"a":1},"d":432,"e":[{"a":{"a":15},"b":"record","c":0}]},{"a":"IsCollected;TweakDBID","b":"IsCollected","c":{"a":1},"d":432,"e":[{"a":{"a":15},"b":"record","c":0}]},{"a":"IsEnabled;","b":"IsEnabled","c":{"a":1},"d":176},{"a":"OnAttach;","b":"OnAttach","d":33},{"a":"OnDropPointRequest;DropPointRequest","b":"OnDropPointRequest","d":50,"e":[{"a":{"a":26,"c":{"b":"DropPointRequest"}},"b":"dropPointRequest","c":0}]},{"a":"OnRegisterDropPointMappinRequest;RegisterDropPointMappinRequest","b":"OnRegisterDropPointMappinRequest","d":50,"e":[{"a":{"a":26,"c":{"b":"RegisterDropPointMappinRequest"}},"b":"request","c":0}]},{"a":"OnRestored;Int32Int32","b":"OnRestored","d":33,"e":[{"a":{"a":6},"b":"saveVersion","c":0},{"a":{"a":6},"b":"gameVersion","c":0}]},{"a":"OnToggleDropPointSystemRequest;ToggleDropPointSystemRequest","b":"OnToggleDropPointSystemRequest","d":50,"e":[{"a":{"a":26,"c":{"b":"ToggleDropPointSystemRequest"}},"b":"request","c":0}]},{"a":"OnUnregisterDropPointMappinRequest;UnregisterDropPointMappinRequest","b":"OnUnregisterDropPointMappinRequest","d":50,"e":[{"a":{"a":26,"c":{"b":"UnregisterDropPointMappinRequest"}},"b":"request","c":0}]},{"a":"RegisterDropPointMappin;DropPointMappinRegistrationData","b":"RegisterDropPointMappin","d":49,"e":[{"a":{"a":26,"c":{"b":"DropPointMappinRegistrationData"}},"b":"data","c":0}]},{"a":"RemoveDropPointSystemLock;CName","b":"RemoveDropPointSystemLock","d":49,"e":[{"a":{"a":14},"b":"reason","c":0}]},{"a":"RemoveMappinData;EntityID","b":"RemoveMappinData","d":49,"e":[{"a":{"b":"entEntityID"},"b":"ownerID","c":0}]},{"a":"RestoreDropPointMappins;Bool","b":"RestoreDropPointMappins","d":49,"e":[{"a":{"a":1},"b":"informDevice","c":4}]},{"a":"UnregisterDropPointMappin;DropPointMappinRegistrationData","b":"UnregisterDropPointMappin","d":49,"e":[{"a":{"a":26,"c":{"b":"DropPointMappinRegistrationData"}},"b":"data","c":0}]},{"a":"UpdatePackage;DropPointRequest","b":"UpdatePackage","d":49,"e":[{"a":{"a":26,"c":{"b":"DropPointRequest"}},"b":"dropPointRequest","c":0}]},{"a":"UpdateRecord;DropPointPackageDropPointPackageStatusPersistentID","b":"UpdateRecord","d":49,"e":[{"a":{"a":26,"c":{"b":"DropPointPackage"}},"b":"package","c":0},{"a":{"b":"DropPointPackageStatus"},"b":"status","c":0},{"a":{"b":"gamePersistentID"},"b":"holder","c":0}]}]}
