{"a":"gameScriptableSystem","b":"FocusCluesSystem","d":0,"e":[{"a":{"a":31,"c":{"b":"LinkedFocusClueData"}},"b":"linkedClues","c":133},{"a":{"a":31,"c":{"a":14}},"b":"disabledGroupes","c":133},{"a":{"b":"LinkedFocusClueData"},"b":"activeLinkedClue","c":129}],"f":[{"a":"AddLinkedClue;script_ref<LinkedFocusClueData>","b":"AddLinkedClue","d":49,"e":[{"a":{"a":28,"c":{"b":"LinkedFocusClueData"}},"b":"clue","c":0}]},{"a":"DisableGroup;CName","b":"DisableGroup","d":49,"e":[{"a":{"a":14},"b":"groupID","c":0}]},{"a":"EnableGroup;CName","b":"EnableGroup","d":49,"e":[{"a":{"a":14},"b":"groupID","c":0}]},{"a":"GetActiveLinkedClue;","b":"GetActiveLinkedClue","c":{"b":"LinkedFocusClueData"},"d":176},{"a":"GetActiveLinkedClueScannableData;","b":"GetActiveLinkedClueScannableData","c":{"a":31,"c":{"b":"gameScanningTooltipElementDef"}},"d":176},{"a":"GetClueGroupData;CNamescript_ref<FocusClueDefinition>","b":"GetClueGroupData","c":{"a":1},"d":176,"e":[{"a":{"a":14},"b":"groupID","c":0},{"a":{"a":28,"c":{"b":"FocusClueDefinition"}},"b":"clue","c":0}]},{"a":"GetLinkedClueGroupData;CNamescript_ref<LinkedFocusClueData>","b":"GetLinkedClueGroupData","c":{"a":1},"d":49,"e":[{"a":{"a":14},"b":"groupID","c":0},{"a":{"a":28,"c":{"b":"LinkedFocusClueData"}},"b":"clue","c":0}]},{"a":"HasLinkedClue;script_ref<LinkedFocusClueData>","b":"HasLinkedClue","c":{"a":1},"d":49,"e":[{"a":{"a":28,"c":{"b":"LinkedFocusClueData"}},"b":"clue","c":0}]},{"a":"IsGroupDisabled;CName","b":"IsGroupDisabled","c":{"a":1},"d":176,"e":[{"a":{"a":14},"b":"groupID","c":0}]},{"a":"IsGroupTagged;script_ref<LinkedFocusClueData>","b":"IsGroupTagged","c":{"a":1},"d":49,"e":[{"a":{"a":28,"c":{"b":"LinkedFocusClueData"}},"b":"clue","c":0}]},{"a":"IsGroupped;EntityIDCName","b":"IsGroupped","c":{"a":1},"d":176,"e":[{"a":{"b":"entEntityID"},"b":"ownerID","c":0},{"a":{"a":14},"b":"groupID","c":2}]},{"a":"IsRegistered;EntityIDCName","b":"IsRegistered","c":{"a":1},"d":176,"e":[{"a":{"b":"entEntityID"},"b":"ownerID","c":0},{"a":{"a":14},"b":"groupID","c":0}]},{"a":"IsTagged;GameObject","b":"IsTagged","c":{"a":1},"d":177,"e":[{"a":{"a":26,"c":{"b":"gameObject"}},"b":"owner","c":0}]},{"a":"OnRegisterLinkedClueRequest;RegisterLinkedCluekRequest","b":"OnRegisterLinkedClueRequest","d":49,"e":[{"a":{"a":26,"c":{"b":"RegisterLinkedCluekRequest"}},"b":"request","c":0}]},{"a":"OnTagLinkedClueRequest;TagLinkedCluekRequest","b":"OnTagLinkedClueRequest","d":49,"e":[{"a":{"a":26,"c":{"b":"TagLinkedCluekRequest"}},"b":"request","c":0}]},{"a":"OnUnregisterLinkedClueRequest;UnregisterLinkedCluekRequest","b":"OnUnregisterLinkedClueRequest","d":49,"e":[{"a":{"a":26,"c":{"b":"UnregisterLinkedCluekRequest"}},"b":"request","c":0}]},{"a":"OnUpdateLinkedCluesRequest;UpdateLinkedClueskRequest","b":"OnUpdateLinkedCluesRequest","d":49,"e":[{"a":{"a":26,"c":{"b":"UpdateLinkedClueskRequest"}},"b":"request","c":0}]},{"a":"RemoveLinkedClue;script_ref<LinkedFocusClueData>","b":"RemoveLinkedClue","d":49,"e":[{"a":{"a":28,"c":{"b":"LinkedFocusClueData"}},"b":"clue","c":0}]},{"a":"RemoveLinkedClueByIndex;Int32","b":"RemoveLinkedClueByIndex","d":49,"e":[{"a":{"a":6},"b":"clueID","c":0}]},{"a":"ResolveLinkedCluesTagging;script_ref<LinkedFocusClueData>Bool","b":"ResolveLinkedCluesTagging","d":49,"e":[{"a":{"a":28,"c":{"b":"LinkedFocusClueData"}},"b":"clue","c":0},{"a":{"a":1},"b":"tag","c":0}]},{"a":"SendlinkedClueTagEvent;script_ref<LinkedFocusClueData>EntityIDBool","b":"SendlinkedClueTagEvent","d":49,"e":[{"a":{"a":28,"c":{"b":"LinkedFocusClueData"}},"b":"linkedClue","c":0},{"a":{"b":"entEntityID"},"b":"requester","c":0},{"a":{"a":1},"b":"tag","c":0}]},{"a":"SendlinkedClueUpdateEvent;script_ref<LinkedFocusClueData>EntityID","b":"SendlinkedClueUpdateEvent","d":49,"e":[{"a":{"a":28,"c":{"b":"LinkedFocusClueData"}},"b":"linkedClue","c":0},{"a":{"b":"entEntityID"},"b":"requester","c":0}]},{"a":"UpdateLinkedClues;script_ref<LinkedFocusClueData>","b":"UpdateLinkedClues","d":49,"e":[{"a":{"a":28,"c":{"b":"LinkedFocusClueData"}},"b":"clue","c":0}]},{"a":"UpdateSingleLinkedClue;LinkedFocusClueData","b":"UpdateSingleLinkedClue","d":49,"e":[{"a":{"b":"LinkedFocusClueData"},"b":"clue","c":0}]}]}
