{"a":"gamedataTweakDBRecord","b":"gamedataVehicleWheelsFrictionMap_Record","c":"VehicleWheelsFrictionMap_Record","d":24,"f":[{"a":"DefaultFrictionPreset","c":{"a":27,"c":{"b":"gamedataVehicleWheelsFrictionPreset_Record"}},"d":4},{"a":"DefaultFrictionPresetHandle","c":{"a":26,"c":{"b":"gamedataVehicleWheelsFrictionPreset_Record"}},"d":4},{"a":"GetSurfacesCount","c":{"a":6},"d":4},{"a":"GetSurfacesItem","c":{"a":27,"c":{"b":"gamedataVehicleSurfaceBinding_Record"}},"d":4,"e":[{"a":{"a":6},"b":"index","c":0}]},{"a":"GetSurfacesItemHandle","c":{"a":26,"c":{"b":"gamedataVehicleSurfaceBinding_Record"}},"d":4,"e":[{"a":{"a":6},"b":"index","c":0}]},{"a":"Surfaces","d":4,"e":[{"a":{"a":31,"c":{"a":27,"c":{"b":"gamedataVehicleSurfaceBinding_Record"}}},"b":"outList","c":2}]},{"a":"SurfacesContains","c":{"a":1},"d":4,"e":[{"a":{"a":27,"c":{"b":"gamedataVehicleSurfaceBinding_Record"}},"b":"item","c":0}]}]}
