{"a":"AIRandomTasks","b":"GetRandomPositionAroundPoint","d":0,"e":[{"a":{"a":26,"c":{"b":"AIArgumentMapping"}},"b":"originPoint","c":128},{"a":{"a":26,"c":{"b":"AIArgumentMapping"}},"b":"distanceMin","c":128},{"a":{"a":26,"c":{"b":"AIArgumentMapping"}},"b":"distanceMax","c":128},{"a":{"a":26,"c":{"b":"AIArgumentMapping"}},"b":"angleMin","c":128},{"a":{"a":26,"c":{"b":"AIArgumentMapping"}},"b":"angleMax","c":128},{"a":{"a":26,"c":{"b":"AIArgumentMapping"}},"b":"outPositionArgument","c":128},{"a":{"b":"Vector4"},"b":"finalPosition","c":130}],"f":[{"a":"Activate;ScriptExecutionContext","b":"Activate","d":34,"e":[{"a":{"b":"AIbehaviorScriptExecutionContext"},"b":"context","c":0}]}]}
