{"a":"AIbehaviorconditionScript","b":"HorizontalLineTrace","d":0,"e":[{"a":{"a":26,"c":{"b":"AIArgumentMapping"}},"b":"source","c":128},{"a":{"a":26,"c":{"b":"AIArgumentMapping"}},"b":"target","c":128},{"a":{"a":26,"c":{"b":"AIArgumentMapping"}},"b":"offset","c":128},{"a":{"a":26,"c":{"b":"AIArgumentMapping"}},"b":"length","c":128},{"a":{"a":26,"c":{"b":"AIArgumentMapping"}},"b":"azimuth","c":128}],"f":[{"a":"Check;ScriptExecutionContext","b":"Check","c":{"b":"AIbehaviorConditionOutcomes"},"d":34,"e":[{"a":{"b":"AIbehaviorScriptExecutionContext"},"b":"context","c":0}]},{"a":"LineTrace;ScriptExecutionContextVector4QuaternionFloat","b":"LineTrace","c":{"a":1},"d":49,"e":[{"a":{"b":"AIbehaviorScriptExecutionContext"},"b":"context","c":0},{"a":{"b":"Vector4"},"b":"queryPosition","c":0},{"a":{"b":"Quaternion"},"b":"queryOrientation","c":0},{"a":{"a":10},"b":"queryLength","c":0}]}]}
