{"a":"inkWidgetLogicController","b":"NetworkMinigameElementController","d":0,"e":[{"a":{"b":"ElementData"},"b":"data","c":130},{"a":{"b":"inkTextWidgetReference"},"b":"text","c":130},{"a":{"b":"Color"},"b":"textNormalColor","c":130},{"a":{"b":"Color"},"b":"textHighlightColor","c":130},{"a":{"b":"inkRectangleWidgetReference"},"b":"bg","c":130},{"a":{"b":"inkWidgetReference"},"b":"colorAccent","c":130},{"a":{"a":10},"b":"dimmedOpacity","c":130},{"a":{"a":10},"b":"notDimmedOpacity","c":130},{"a":{"a":6},"b":"defaultFontSize","c":130},{"a":{"a":1},"b":"wasConsumed","c":130},{"a":{"a":27,"c":{"b":"inkWidget"}},"b":"root","c":129}],"f":[{"a":"OnInitialize","c":{"a":1},"d":98},{"a":"Consume;","b":"Consume","d":32},{"a":"GetContent;","b":"GetContent","c":{"b":"ElementData"},"d":48},{"a":"GetContentWidget;","b":"GetContentWidget","c":{"b":"inkWidgetReference"},"d":48},{"a":"RefreshColorAccent;","b":"RefreshColorAccent","d":48},{"a":"SetAsBufferSlot;","b":"SetAsBufferSlot","d":48},{"a":"SetContent;script_ref<ElementData>","b":"SetContent","d":32,"e":[{"a":{"a":28,"c":{"b":"ElementData"}},"b":"toSet","c":0}]},{"a":"SetElementActive;Bool","b":"SetElementActive","d":48,"e":[{"a":{"a":1},"b":"isDimmed","c":0}]},{"a":"SetHighlightStatus;Bool","b":"SetHighlightStatus","d":32,"e":[{"a":{"a":1},"b":"doHighlight","c":0}]}]}
