{"a":"inkWidgetLogicController","b":"PaginationController","d":0,"e":[{"a":{"b":"inkHorizontalPanelWidgetReference"},"b":"paginationRoot","c":129},{"a":{"b":"inkWidgetReference"},"b":"nextArrow","c":128},{"a":{"b":"inkWidgetReference"},"b":"previousArrow","c":128},{"a":{"a":31,"c":{"a":27,"c":{"b":"PaginationNumberController"}}},"b":"paginationNumbers","c":129},{"a":{"a":6},"b":"halfPaginationDisplay","c":129},{"a":{"a":6},"b":"fullPaginationDisplay","c":129}],"f":[{"a":"OnUninitialize","c":{"a":1},"d":98},{"a":"CreatePageNumber;Int32","b":"CreatePageNumber","d":49,"e":[{"a":{"a":6},"b":"number","c":0}]},{"a":"GetPaginationNumbers;","b":"GetPaginationNumbers","c":{"a":31,"c":{"a":27,"c":{"b":"PaginationNumberController"}}},"d":48},{"a":"SetActivePageNumber;Int32","b":"SetActivePageNumber","d":48,"e":[{"a":{"a":6},"b":"index","c":0}]},{"a":"SetData;Int32","b":"SetData","d":48,"e":[{"a":{"a":6},"b":"pageCount","c":0}]}]}
