{"b":"questPlayVoiceset_NodeTypeParams","d":8,"g":true,"e":[{"a":{"b":"gameEntityReference"},"b":"puppetRef","c":128},{"a":{"a":1},"b":"isPlayer","c":128},{"a":{"a":14},"b":"voicesetName","c":128},{"a":{"a":1},"b":"useVoicesetSystem","c":128},{"a":{"a":1},"b":"playOnlyGrunt","c":128},{"a":{"b":"locVoiceoverContext"},"b":"overridingVoiceoverContext","c":128},{"a":{"a":1},"b":"overrideVoiceoverExpression","c":128},{"a":{"b":"locVoiceoverExpression"},"b":"overridingVoiceoverExpression","c":128},{"a":{"a":1},"b":"overrideVisualStyle","c":128},{"a":{"b":"scnDialogLineVisualStyle"},"b":"overridingVisualStyle","c":128}]}
