{"a":"BaseCodexLinkController","b":"QuestMappinLinkController","d":0,"e":[{"a":{"a":26,"c":{"b":"gameJournalQuestMapPinBase"}},"b":"mappinEntry","c":129},{"a":{"a":26,"c":{"b":"gameJournalQuestMapPinBase"}},"b":"mappinEntryHash","c":129},{"a":{"b":"Vector3"},"b":"jumpTo","c":129},{"a":{"a":6},"b":"hash","c":129},{"a":{"a":1},"b":"isTracked","c":129}],"f":[{"a":"OnActivateLink","c":{"a":1},"d":98,"e":[{"a":{"a":26,"c":{"b":"ActivateMapLink"}},"b":"e","c":0}]},{"a":"Activate;","b":"Activate","d":33},{"a":"Setup;JournalQuestMapPinBaseInt32Vector3Bool","b":"Setup","d":48,"e":[{"a":{"a":26,"c":{"b":"gameJournalQuestMapPinBase"}},"b":"mappinEntry","c":0},{"a":{"a":6},"b":"mappinHash","c":0},{"a":{"b":"Vector3"},"b":"jumpTo","c":0},{"a":{"a":1},"b":"isTracked","c":0}]}]}
