{"a":"inkWidgetLogicController","b":"SingleCooldownManager","d":0,"e":[{"a":{"b":"inkImageWidgetReference"},"b":"sprite","c":129},{"a":{"b":"inkImageWidgetReference"},"b":"spriteBg","c":129},{"a":{"b":"inkImageWidgetReference"},"b":"icon","c":129},{"a":{"b":"ECooldownGameControllerMode"},"b":"type","c":129},{"a":{"b":"inkTextWidgetReference"},"b":"name","c":129},{"a":{"b":"inkTextWidgetReference"},"b":"desc","c":129},{"a":{"b":"inkTextWidgetReference"},"b":"timeRemaining","c":129},{"a":{"b":"inkTextWidgetReference"},"b":"stackCount","c":129},{"a":{"b":"inkRectangleWidgetReference"},"b":"fill","c":129},{"a":{"a":10},"b":"outroDuration","c":129},{"a":{"b":"Vector2"},"b":"fullSizeValue","c":129},{"a":{"a":10},"b":"initialDuration","c":129},{"a":{"b":"ECooldownIndicatorState"},"b":"state","c":129},{"a":{"b":"inkCompoundWidgetReference"},"b":"pool","c":129},{"a":{"b":"inkCompoundWidgetReference"},"b":"grid","c":129},{"a":{"a":26,"c":{"b":"inkanimProxy"}},"b":"currentAnimProxy","c":129},{"a":{"b":"UIBuffInfo"},"b":"buffData","c":129},{"a":{"a":12},"b":"defaultTimeRemainingText","c":129},{"a":{"a":15},"b":"excludedStatusEffect","c":129},{"a":{"a":12},"b":"C_EXCLUDED_STATUS_EFFECT_NAME","c":129}],"f":[{"a":"OnFillIntroAnimationOver","c":{"a":1},"d":98,"e":[{"a":{"a":26,"c":{"b":"inkanimProxy"}},"b":"proxy","c":0}]},{"a":"OnFillOutroAnimationOver","c":{"a":1},"d":98,"e":[{"a":{"a":26,"c":{"b":"inkanimProxy"}},"b":"proxy","c":0}]},{"a":"ActivateCooldown;UIBuffInfo","b":"ActivateCooldown","d":48,"e":[{"a":{"b":"UIBuffInfo"},"b":"buffData","c":0}]},{"a":"ConvertFloatToTime;FloatGameTimeInt32Int32","b":"ConvertFloatToTime","d":177,"e":[{"a":{"a":10},"b":"f","c":0},{"a":{"b":"GameTime"},"b":"time","c":2},{"a":{"a":6},"b":"totalSeconds","c":2},{"a":{"a":6},"b":"fraction","c":2}]},{"a":"FillIntroAnimationStart;","b":"FillIntroAnimationStart","d":49},{"a":"FillOutroAnimationStart;","b":"FillOutroAnimationStart","d":49},{"a":"GetState;","b":"GetState","c":{"b":"ECooldownIndicatorState"},"d":48},{"a":"HideCooldownWidget;","b":"HideCooldownWidget","d":49},{"a":"Init;inkCompoundRefinkCompoundRef","b":"Init","d":48,"e":[{"a":{"b":"inkCompoundWidgetReference"},"b":"pool","c":0},{"a":{"b":"inkCompoundWidgetReference"},"b":"grid","c":0}]},{"a":"IsIDMatch;TweakDBID","b":"IsIDMatch","c":{"a":1},"d":48,"e":[{"a":{"a":15},"b":"id","c":0}]},{"a":"RemoveCooldown;","b":"RemoveCooldown","d":48},{"a":"SetStackCount;Int32","b":"SetStackCount","d":49,"e":[{"a":{"a":6},"b":"count","c":0}]},{"a":"SetTimeRemaining;Float","b":"SetTimeRemaining","d":49,"e":[{"a":{"a":10},"b":"time","c":0}]},{"a":"Update;FloatUint32","b":"Update","d":48,"e":[{"a":{"a":10},"b":"timeLeft","c":0},{"a":{"a":7},"b":"stackCount","c":0}]}]}
