{"a":"gamebbScriptDefinition","b":"UI_ScannerDef","d":0,"e":[{"a":{"b":"gamebbScriptID_Variant"},"b":"Scannables","c":128},{"a":{"b":"gamebbScriptID_Float"},"b":"CurrentProgress","c":128},{"a":{"b":"gamebbScriptID_Variant"},"b":"CurrentState","c":128},{"a":{"b":"gamebbScriptID_String"},"b":"ProgressBarText","c":128},{"a":{"b":"gamebbScriptID_EntityID"},"b":"ScannedObject","c":128},{"a":{"b":"gamebbScriptID_Variant"},"b":"ScannerMode","c":128},{"a":{"b":"gamebbScriptID_Int32"},"b":"scannerTooltip","c":128},{"a":{"b":"gamebbScriptID_Bool"},"b":"scannerChangeTargetTooltipVisibility","c":128},{"a":{"b":"gamebbScriptID_Variant"},"b":"scannerData","c":128},{"a":{"b":"gamebbScriptID_Float"},"b":"scannerObjectDistance","c":128},{"a":{"b":"gamebbScriptID_Variant"},"b":"scannerObjectStats","c":128},{"a":{"b":"gamebbScriptID_Int32"},"b":"scannerQuickHackActionId","c":128},{"a":{"b":"gamebbScriptID_Bool"},"b":"scannerQuickHackActionStarted","c":128},{"a":{"b":"gamebbScriptID_Float"},"b":"scannerQuickHackTime","c":128},{"a":{"b":"gamebbScriptID_Bool"},"b":"exclusiveFocusActive","c":128},{"a":{"b":"gamebbScriptID_Variant"},"b":"LastTaggedTarget","c":128},{"a":{"b":"gamebbScriptID_Variant"},"b":"skillCheckInfo","c":128},{"a":{"b":"gamebbScriptID_Bool"},"b":"ShowHudHintMessege","c":128},{"a":{"b":"gamebbScriptID_String"},"b":"HudHintMessegeContent","c":128},{"a":{"b":"gamebbScriptID_Bool"},"b":"UIVisible","c":128},{"a":{"b":"gamebbScriptID_Bool"},"b":"ScannerLookAt","c":128},{"a":{"b":"gamebbScriptID_Variant"},"b":"scannerActiveTab","c":128},{"a":{"b":"gamebbScriptID_Bool"},"b":"twintoneAvailable","c":128},{"a":{"b":"gamebbScriptID_Bool"},"b":"twintoneApplyAvailable","c":128},{"a":{"b":"gamebbScriptID_Bool"},"b":"twintoneNoModelAvailable","c":128}],"f":[{"a":"AutoCreateInSystem;","b":"AutoCreateInSystem","c":{"a":1},"d":176}]}
