{"a":"UpperBodyTransition","b":"UpperBodyEventsTransition","d":4,"e":[{"a":{"a":1},"b":"switchButtonPushed","c":128},{"a":{"a":1},"b":"cyclePushed","c":128},{"a":{"a":10},"b":"delay","c":128},{"a":{"a":10},"b":"cycleBlock","c":128},{"a":{"a":1},"b":"switchPending","c":128},{"a":{"a":6},"b":"counter","c":128}],"f":[{"a":"CheckSwitchInput;StateContextStateGameScriptInterface","b":"CheckSwitchInput","c":{"a":1},"d":50,"e":[{"a":{"a":26,"c":{"b":"gamestateMachineStateContextScript"}},"b":"stateContext","c":0},{"a":{"a":26,"c":{"b":"gamestateMachineGameScriptInterface"}},"b":"scriptInterface","c":0}]},{"a":"OnEnter;StateContextStateGameScriptInterface","b":"OnEnter","d":34,"e":[{"a":{"a":26,"c":{"b":"gamestateMachineStateContextScript"}},"b":"stateContext","c":0},{"a":{"a":26,"c":{"b":"gamestateMachineGameScriptInterface"}},"b":"scriptInterface","c":0}]},{"a":"OnExit;StateContextStateGameScriptInterface","b":"OnExit","d":34,"e":[{"a":{"a":26,"c":{"b":"gamestateMachineStateContextScript"}},"b":"stateContext","c":0},{"a":{"a":26,"c":{"b":"gamestateMachineGameScriptInterface"}},"b":"scriptInterface","c":0}]},{"a":"QueueActionBlocked;StateGameScriptInterface","b":"QueueActionBlocked","d":50,"e":[{"a":{"a":26,"c":{"b":"gamestateMachineGameScriptInterface"}},"b":"scriptInterface","c":0}]},{"a":"ResetEquipVars;StateContext","b":"ResetEquipVars","d":34,"e":[{"a":{"a":26,"c":{"b":"gamestateMachineStateContextScript"}},"b":"stateContext","c":0}]},{"a":"SyncEquipVarsToPermanentStorage;StateContext","b":"SyncEquipVarsToPermanentStorage","d":34,"e":[{"a":{"a":26,"c":{"b":"gamestateMachineStateContextScript"}},"b":"stateContext","c":0}]},{"a":"UpdateSwitchItem;FloatStateContextStateGameScriptInterface","b":"UpdateSwitchItem","c":{"a":1},"d":50,"e":[{"a":{"a":10},"b":"timeDelta","c":0},{"a":{"a":26,"c":{"b":"gamestateMachineStateContextScript"}},"b":"stateContext","c":0},{"a":{"a":26,"c":{"b":"gamestateMachineGameScriptInterface"}},"b":"scriptInterface","c":0}]}]}
