{"a":"BaseButtonView","b":"VehicleBrandFilterLogicController","d":0,"e":[{"a":{"b":"inkImageWidgetReference"},"b":"brandLogo","c":129},{"a":{"b":"inkTextWidgetReference"},"b":"brandText","c":129},{"a":{"a":14},"b":"brand","c":129},{"a":{"a":12},"b":"brandAsString","c":129},{"a":{"b":"EVehicleBrandState"},"b":"state","c":129},{"a":{"a":1},"b":"isHovered","c":129},{"a":{"a":27,"c":{"b":"inkWidget"}},"b":"styleWidget","c":129},{"a":{"a":31,"c":{"a":14}},"b":"newOffers","c":129}],"f":[{"a":"OnInitialize","c":{"a":1},"d":98},{"a":"AddNewOffer;CName","b":"AddNewOffer","d":48,"e":[{"a":{"a":14},"b":"offerFact","c":0}]},{"a":"ButtonStateChanged;inkEButtonStateinkEButtonState","b":"ButtonStateChanged","d":34,"e":[{"a":{"b":"inkEButtonState"},"b":"oldState","c":0},{"a":{"b":"inkEButtonState"},"b":"newState","c":0}]},{"a":"GetBrand;","b":"GetBrand","c":{"a":14},"d":48},{"a":"HasNewOffers;","b":"HasNewOffers","c":{"a":1},"d":48},{"a":"RefreshState;","b":"RefreshState","d":48},{"a":"RemoveNewOffer;CName","b":"RemoveNewOffer","d":48,"e":[{"a":{"a":14},"b":"offerFact","c":0}]},{"a":"SetHoverState;Bool","b":"SetHoverState","d":48,"e":[{"a":{"a":1},"b":"isHovered","c":0}]},{"a":"SetUp;CNameEVehicleBrandState","b":"SetUp","d":48,"e":[{"a":{"a":14},"b":"brand","c":0},{"a":{"b":"EVehicleBrandState"},"b":"state","c":0}]},{"a":"StateValueToName;EVehicleBrandState","b":"StateValueToName","c":{"a":14},"d":49,"e":[{"a":{"b":"EVehicleBrandState"},"b":"state","c":0}]},{"a":"UpdateState;EVehicleBrandState","b":"UpdateState","d":48,"e":[{"a":{"b":"EVehicleBrandState"},"b":"state","c":0}]}]}
